mobilecoin/__init__.py
mobilecoin/cli.py
mobilecoin/client.py
mobilecoin/client_v1.py
mobilecoin/token.py
mobilecoin/util/__init__.py
mobilecoin/util/external_pb2.py
mobilecoin/util/printable_pb2.py
mobilecoin/util/setup.py
mobilecoin-2.3.1.dist-info/METADATA
mobilecoin-2.3.1.dist-info/WHEEL
mobilecoin-2.3.1.dist-info/entry_points.txt
mobilecoin-2.3.1.dist-info/RECORD
