Metadata-Version: 2.1
Name: mobilecoin
Version: 2.3.1
Summary: 
Home-page: https://mobilecoin.com/
Author: Christian Oudard
Requires-Python: >=3.10,<4.0
Classifier: Programming Language :: Python :: 3
Classifier: Programming Language :: Python :: 3.10
Classifier: Programming Language :: Python :: 3.11
Requires-Dist: aiohttp (>=3.8.3,<4.0.0)
Requires-Dist: base58 (>=2.1.1,<3.0.0)
Requires-Dist: protobuf (>=4.21.12,<5.0.0)
Requires-Dist: segno (>=1.5.2,<2.0.0)
Project-URL: Repository, https://github.com/mobilecoinofficial/full-service
